mxmul_pkg/__init__.py
mxmul_pkg/mxmul.py
mxmulaac_pkg/__init__.py
mxmulaac_pkg/mxmul.py
mxmulaac_pkg-1.0.dist-info/LICENSE
mxmulaac_pkg-1.0.dist-info/METADATA
mxmulaac_pkg-1.0.dist-info/WHEEL
mxmulaac_pkg-1.0.dist-info/top_level.txt
mxmulaac_pkg-1.0.dist-info/RECORD
