Metadata-Version: 2.1
Name: mxmulaac-pkg
Version: 1.0
Summary: An example for teaching how to publish a Python package
Home-page: UNKNOWN
Author: bigskeleton
Author-email: bigskeleton@gmail.com
License: UNKNOWN
Platform: UNKNOWN
Classifier: Operating System :: OS Independent
Classifier: License :: OSI Approved :: MIT License
